iniutil/__init__.py
iniutil/parser.py
tests/__init__.py
tests/test_parser.py
iniutil-1.0.4.dist-info/LICENSE
iniutil-1.0.4.dist-info/METADATA
iniutil-1.0.4.dist-info/WHEEL
iniutil-1.0.4.dist-info/top_level.txt
iniutil-1.0.4.dist-info/RECORD
