Metadata-Version: 2.1
Name: iniutil
Version: 1.0.4
Summary: Python parser for ini files.
Author-email: Akeem Amusat <hi@olayml.xyz>
Project-URL: Homepage, https://github.com/aoamusat/iniutil
Project-URL: Issues, https://github.com/aoamusat/iniutil/issues
Classifier: Programming Language :: Python :: 3
Classifier: License :: OSI Approved :: MIT License
Classifier: Operating System :: OS Independent
Requires-Python: >=3.8
License-File: LICENSE
